llm_electronhub.py
llm_electronhub-0.1.dist-info/licenses/LICENSE
llm_electronhub-0.1.dist-info/METADATA
llm_electronhub-0.1.dist-info/WHEEL
llm_electronhub-0.1.dist-info/entry_points.txt
llm_electronhub-0.1.dist-info/top_level.txt
llm_electronhub-0.1.dist-info/RECORD
