Metadata-Version: 2.4
Name: llm-electronhub
Version: 0.1
Summary: LLM plugin for models hosted by ElectronHub
Author: Olivia
License: Apache-2.0
Project-URL: Homepage, https://github.com/taygetea/llm-electronhub
Classifier: License :: OSI Approved :: Apache Software License
License-File: LICENSE
Requires-Dist: llm>=0.27.1
Requires-Dist: httpx
Requires-Dist: openai>=1.57.0
Provides-Extra: test
Requires-Dist: pytest; extra == "test"
Requires-Dist: pytest-recording; extra == "test"
Requires-Dist: inline-snapshot; extra == "test"
Dynamic: license-file
